odoo/addons/scrap_reason_code/README.rst
odoo/addons/scrap_reason_code/__init__.py
odoo/addons/scrap_reason_code/__manifest__.py
odoo/addons/scrap_reason_code/i18n/es.po
odoo/addons/scrap_reason_code/i18n/fr.po
odoo/addons/scrap_reason_code/i18n/it.po
odoo/addons/scrap_reason_code/i18n/scrap_reason_code.pot
odoo/addons/scrap_reason_code/models/__init__.py
odoo/addons/scrap_reason_code/models/reason_code.py
odoo/addons/scrap_reason_code/models/stock_move.py
odoo/addons/scrap_reason_code/models/stock_scrap.py
odoo/addons/scrap_reason_code/readme/CONFIGURE.md
odoo/addons/scrap_reason_code/readme/CONTRIBUTORS.md
odoo/addons/scrap_reason_code/readme/CREDITS.md
odoo/addons/scrap_reason_code/readme/DESCRIPTION.md
odoo/addons/scrap_reason_code/readme/ROADMAP.md
odoo/addons/scrap_reason_code/readme/USAGE.md
odoo/addons/scrap_reason_code/security/ir.model.access.csv
odoo/addons/scrap_reason_code/static/description/icon.png
odoo/addons/scrap_reason_code/static/description/index.html
odoo/addons/scrap_reason_code/tests/__init__.py
odoo/addons/scrap_reason_code/tests/test_scrap_reason_code.py
odoo/addons/scrap_reason_code/views/reason_code_view.xml
odoo/addons/scrap_reason_code/views/stock_move_views.xml
odoo/addons/scrap_reason_code/views/stock_scrap_views.xml
odoo_addon_scrap_reason_code-18.0.1.0.0.2.dist-info/METADATA
odoo_addon_scrap_reason_code-18.0.1.0.0.2.dist-info/WHEEL
odoo_addon_scrap_reason_code-18.0.1.0.0.2.dist-info/top_level.txt
odoo_addon_scrap_reason_code-18.0.1.0.0.2.dist-info/RECORD
